hephaistus/__init__.py
hephaistus/god_of_forges.py
hephaistus/models/Modelfile_developer
hephaistus/models/Modelfile_devops_engineer
hephaistus/models/Modelfile_hephaestus
hephaistus/models/Modelfile_mudlark
hephaistus/utils.py
hephaistus-1.2.1.dist-info/LICENSE
hephaistus-1.2.1.dist-info/METADATA
hephaistus-1.2.1.dist-info/WHEEL
hephaistus-1.2.1.dist-info/RECORD
