Metadata-Version: 2.3
Name: hephAIstus
Version: 1.2.1
Summary: Local AI tools and models for DevOps Engineers
License: Creative Commons Legal Code
Author: JacobCompany
Author-email: jacob.gross@health-union.com
Requires-Python: <4.0,>=3.11
Classifier: License :: Other/Proprietary License
Classifier: Programming Language :: Python :: 3
Classifier: Programming Language :: Python :: 3.11
Classifier: Programming Language :: Python :: 3.12
Classifier: Programming Language :: Python :: 3.13
Requires-Dist: gpt4all (>=2.8,<3.0)
Requires-Dist: ollama (>=0.5,<1.0)
Requires-Dist: pandas (>=2.3.0,<3.0.0)
Requires-Dist: pypdf (>=5.6.0,<6.0.0)
Requires-Dist: python-docx (>=1.1.2,<2.0.0)
Requires-Dist: python-pptx (>=1.0.2,<2.0.0)
